{
  "name": "gh-feed",
  "alias": "gh-feed",
  "version": 2,
  "regions": [
    "sfo1",
    "bru1"
  ],
  "functions": {
    "bootstrap": {
      "runtime": "now-custom-runtime@0.0.4",
      "includeFiles": "cacert.pem"
    },
    "package.json": {
      "runtime": "@now/static-build@0.14.0"
    }
  },
  "rewrites": [
    {
      "source": "/api",
      "destination": "bootstrap"
    },
    {
      "source": "/favicon.ico",
      "destination": "/favicon.ico"
    },
    {
      "source": "/asset-manifest.json",
      "destination": "/asset-manifest.json"
    },
    {
      "source": "/manifest.json",
      "destination": "/manifest.json"
    },
    {
      "source": "/precache-manifest.(.*)",
      "destination": "/precache-manifest.$1"
    },
    {
      "source": "/static/(.*)",
      "destination": "/static/$1"
    },
    {
      "source": "/.*",
      "destination": "/index.html"
    }
  ]
}
